awk_plus_plus/__init__.py
awk_plus_plus/cli.py
awk_plus_plus/plugin_manager.py
awk_plus_plus/webapp.py
awk_plus_plus/interpreter/__init__.py
awk_plus_plus/interpreter/interpreter.py
awk_plus_plus/interpreter/sql_macros.py
awk_plus_plus/interpreter/std.py
awk_plus_plus/io/__init__.py
awk_plus_plus/io/assets.py
awk_plus_plus/io/http.py
awk_plus_plus-0.17.1.dist-info/LICENSE.txt
awk_plus_plus-0.17.1.dist-info/METADATA
awk_plus_plus-0.17.1.dist-info/WHEEL
awk_plus_plus-0.17.1.dist-info/entry_points.txt
awk_plus_plus-0.17.1.dist-info/top_level.txt
awk_plus_plus-0.17.1.dist-info/RECORD
