Metadata-Version: 2.1
Name: awk_plus_plus
Version: 0.17.1
Summary: Declarative Data Orchestration
Home-page: https://github.com/pyscaffold/pyscaffold/
Author: sanchezcarlosjr
Author-email: 24639141+sanchezcarlosjr@users.noreply.github.com
License: MIT
Project-URL: Documentation, https://pyscaffold.org/
Platform: any
Classifier: Development Status :: 4 - Beta
Classifier: Programming Language :: Python
License-File: LICENSE.txt
Requires-Dist: typer[all]
Requires-Dist: gradio
Requires-Dist: pydantic
Requires-Dist: pandas
Requires-Dist: numpy
Requires-Dist: fastapi
Requires-Dist: keyring
Requires-Dist: jsonnet
Requires-Dist: jq
Requires-Dist: dask
Requires-Dist: kink
Requires-Dist: python-magic
Requires-Dist: hishel
Requires-Dist: tenacity
Requires-Dist: httpx[http2]
Requires-Dist: sqlmesh
Requires-Dist: pluggy
Requires-Dist: pyarrow
Requires-Dist: openpyxl >=3.1.0
Requires-Dist: duckdb
Requires-Dist: importlib-metadata ; python_version < "3.10"
Provides-Extra: testing
Requires-Dist: setuptools ; extra == 'testing'
Requires-Dist: pytest ; extra == 'testing'
Requires-Dist: pytest-cov ; extra == 'testing'
